Workbook

Sheet Readme
A1: Include_Relationship
A2: This work sheet illustrates the include/reference relationship between XX code files.
A3: Field Name | B3: Description
A4: XX_file_full_path | B4: The full path of source XX code. XX code full path=Folder+XX file name
A5: XX_file_folder | B5: The folder directory of the XX code file
A6: XX_file_name | B6: The name of the XX code file
A7: line_no | B7: The line number where another XX code is included in the source code
A8: Included_File_Name | B8: The XX code file referenced by the source code
A10: Frequency
A11: This worksheet records the number of times a XX file is included or referenced by other files.
A12: It identifies which XX code serve general business needs and which are dedicated to specific business scenarios.
A14: Extension/TODO
A15: The Data in Include_Relationship sheet can be used to detect which XX code is orphan.
A16: Required Data:
A17: Include_Relationship.XX code full path
A18: Include_Relationship.Included File Name
A19: Task Scheduler information

Sheet Include_Relationship
A1: XX_file_full_path | B1: XX_file_folder | C1: XX_file_name | D1: line_no | E1: Included_File_Name
A2: XX Program - 254(166 XX; 86 eSpace )\Daily -122 (65 XX; 57 eSpace )\Amort NIIAmort Fee -1\OGL_Remap_Daily.txt | B2: =IFERROR(LEFT(A2,FIND("~",SUBSTITUTE(A2,"\","~",LEN(A2)-LEN(SUBSTITUTE(A2,"\",""))))),"") | C2: =IFERROR(MID(A2,FIND("~",SUBSTITUTE(A2,"\","~",LEN(A2)-LEN(SUBSTITUTE(A2,"\",""))))+1,LEN(A2)),A2) | D2: 3 | E2: p:\libname.txt
A3: XX Program - 254(166 XX; 86 eSpace )\Daily -122 (65 XX; 57 eSpace )\CASA Trend Report -1\Daily_CASA_Trend4.txt | B3: =IFERROR(LEFT(A3,FIND("~",SUBSTITUTE(A3,"\","~",LEN(A3)-LEN(SUBSTITUTE(A3,"\",""))))),"") | C3: =IFERROR(MID(A3,FIND("~",SUBSTITUTE(A3,"\","~",LEN(A3)-LEN(SUBSTITUTE(A3,"\",""))))+1,LEN(A3)),A3) | D3: 7 | E3: p:\libname.txt
A4: XX Program - 254(166 XX; 86 eSpace )\Daily -122 (65 XX; 57 eSpace )\CASA Trend Report -1\Daily_CASA_Trend4.txt | B4: =IFERROR(LEFT(A4,FIND("~",SUBSTITUTE(A4,"\","~",LEN(A4)-LEN(SUBSTITUTE(A4,"\",""))))),"") | C4: =IFERROR(MID(A4,FIND("~",SUBSTITUTE(A4,"\","~",LEN(A4)-LEN(SUBSTITUTE(A4,"\",""))))+1,LEN(A4)),A4) | D4: 11 | E4: E:\XX\Revenue by RM\Macro\Set_Macro.txt
A5: XX Program - 254(166 XX; 86 eSpace )\Daily -122 (65 XX; 57 eSpace )\Check IMH availability -1\Daily_IW_Check2.txt | B5: =IFERROR(LEFT(A5,FIND("~",SUBSTITUTE(A5,"\","~",LEN(A5)-LEN(SUBSTITUTE(A5,"\",""))))),"") | C5: =IFERROR(MID(A5,FIND("~",SUBSTITUTE(A5,"\","~",LEN(A5)-LEN(SUBSTITUTE(A5,"\",""))))+1,LEN(A5)),A5) | D5: 1 | E5: p:\libname.txt
A6: XX Program - 254(166 XX; 86 eSpace )\Daily -122 (65 XX; 57 eSpace )\Check IMH FTP table -1\Daily_TP_Check.txt | B6: =IFERROR(LEFT(A6,FIND("~",SUBSTITUTE(A6,"\","~",LEN(A6)-LEN(SUBSTITUTE(A6,"\",""))))),"") | C6: =IFERROR(MID(A6,FIND("~",SUBSTITUTE(A6,"\","~",LEN(A6)-LEN(SUBSTITUTE(A6,"\",""))))+1,LEN(A6)),A6) | D6: 1 | E6: p:\libname.txt
A7: XX Program - 254(166 XX; 86 eSpace )\Daily -122 (65 XX; 57 eSpace )\Check SIC change -1\Daily_Customer_SIC_EJM_Movement2.txt | B7: =IFERROR(LEFT(A7,FIND("~",SUBSTITUTE(A7,"\","~",LEN(A7)-LEN(SUBSTITUTE(A7,"\",""))))),"") | C7: =IFERROR(MID(A7,FIND("~",SUBSTITUTE(A7,"\","~",LEN(A7)-LEN(SUBSTITUTE(A7,"\",""))))+1,LEN(A7)),A7) | D7: 1 | E7: p:\libname.txt
A8: XX Program - 254(166 XX; 86 eSpace )\Daily -122 (65 XX; 57 eSpace )\Check SIC change -1\Daily_Customer_SIC_EJM_Movement2.txt | B8: =IFERROR(LEFT(A8,FIND("~",SUBSTITUTE(A8,"\","~",LEN(A8)-LEN(SUBSTITUTE(A8,"\",""))))),"") | C8: =IFERROR(MID(A8,FIND("~",SUBSTITUTE(A8,"\","~",LEN(A8)-LEN(SUBSTITUTE(A8,"\",""))))+1,LEN(A8)),A8) | D8: 9 | E8: E:\XX\Revenue by RM\Macro\Set_Macro.txt
A9: XX Program - 254(166 XX; 86 eSpace )\Daily -122 (65 XX; 57 eSpace )\CRM Customer Group -1\a1.2_crm_customer_group.txt | B9: =IFERROR(LEFT(A9,FIND("~",SUBSTITUTE(A9,"\","~",LEN(A9)-LEN(SUBSTITUTE(A9,"\",""))))),"") | C9: =IFERROR(MID(A9,FIND("~",SUBSTITUTE(A9,"\","~",LEN(A9)-LEN(SUBSTITUTE(A9,"\",""))))+1,LEN(A9)),A9) | D9: 1 | E9: P:\Libname.txt
A10: XX Program - 254(166 XX; 86 eSpace )\Daily -122 (65 XX; 57 eSpace )\Dailiy New Loan Pricing -1\Daily_New_Loan_Pricing3.txt | B10: =IFERROR(LEFT(A10,FIND("~",SUBSTITUTE(A10,"\","~",LEN(A10)-LEN(SUBSTITUTE(A10,"\",""))))),"") | C10: =IFERROR(MID(A10,FIND("~",SUBSTITUTE(A10,"\","~",LEN(A10)-LEN(SUBSTITUTE(A10,"\",""))))+1,LEN(A10)),A10) | D10: 1 | E10: p:\libname.txt
A11: XX Program - 254(166 XX; 86 eSpace )\Daily -122 (65 XX; 57 eSpace )\Daily Batch -18\Daily_Bills_Turnover2.txt | B11: =IFERROR(LEFT(A11,FIND("~",SUBSTITUTE(A11,"\","~",LEN(A11)-LEN(SUBSTITUTE(A11,"\",""))))),"") | C11: =IFERROR(MID(A11,FIND("~",SUBSTITUTE(A11,"\","~",LEN(A11)-LEN(SUBSTITUTE(A11,"\",""))))+1,LEN(A11)),A11) | D11: 1 | E11: p:\libname.txt
A12: XX Program - 254(166 XX; 86 eSpace )\Daily -122 (65 XX; 57 eSpace )\Daily Batch -18\Daily_Bills_Turnover2.txt | B12: =IFERROR(LEFT(A12,FIND("~",SUBSTITUTE(A12,"\","~",LEN(A12)-LEN(SUBSTITUTE(A12,"\",""))))),"") | C12: =IFERROR(MID(A12,FIND("~",SUBSTITUTE(A12,"\","~",LEN(A12)-LEN(SUBSTITUTE(A12,"\",""))))+1,LEN(A12)),A12) | D12: 35 | E12: &Macro_Path.Set_Macro.txt
A13: XX Program - 254(166 XX; 86 eSpace )\Daily -122 (65 XX; 57 eSpace )\Daily Batch -18\Daily_Bill_Commission_and_Interest.txt | B13: =IFERROR(LEFT(A13,FIND("~",SUBSTITUTE(A13,"\","~",LEN(A13)-LEN(SUBSTITUTE(A13,"\",""))))),"") | C13: =IFERROR(MID(A13,FIND("~",SUBSTITUTE(A13,"\","~",LEN(A13)-LEN(SUBSTITUTE(A13,"\",""))))+1,LEN(A13)),A13) | D13: 9 | E13: p:\libname.txt
... A181: XX Program - 254(166 XX; 86 eSpace )\Monthly -117 (89 XX; 28 eSpace)\Customer_Profile.txt | B181: =IFERROR(LEFT(A181,FIND("~",SUBSTITUTE(A181,"\","~",LEN(A181)-LEN(SUBSTITUTE(A181,"\",""))))),"") | C181: =IFERROR(MID(A181,FIND("~",SUBSTITUTE(A181,"\","~",LEN(A181)-LEN(SUBSTITUTE(A181,"\",""))))+1,LEN(A181)),A181) | D181: 3445 | E181: E:\XX\Revenue by RM\adhoc\Monthly_Issue_Bank.txt
A182: XX Program - 254(166 XX; 86 eSpace )\Monthly -117 (89 XX; 28 eSpace)\Customer_Profile.txt | B182: =IFERROR(LEFT(A182,FIND("~",SUBSTITUTE(A182,"\","~",LEN(A182)-LEN(SUBSTITUTE(A182,"\",""))))),"") | C182: =IFERROR(MID(A182,FIND("~",SUBSTITUTE(A182,"\","~",LEN(A182)-LEN(SUBSTITUTE(A182,"\",""))))+1,LEN(A182)),A182) | D182: 4228 | E182: E:\XX\Revenue by RM\adhoc\Corp_Prem_Rolling.txt | F182: has
A183: XX Program - 254(166 XX; 86 eSpace )\Monthly -117 (89 XX; 28 eSpace)\Customer_Profile.txt | B183: =IFERROR(LEFT(A183,FIND("~",SUBSTITUTE(A183,"\","~",LEN(A183)-LEN(SUBSTITUTE(A183,"\",""))))),"") | C183: =IFERROR(MID(A183,FIND("~",SUBSTITUTE(A183,"\","~",LEN(A183)-LEN(SUBSTITUTE(A183,"\",""))))+1,LEN(A183)),A183) | D183: 4265 | E183: E:\XX\Revenue by RM\adhoc\SBLC_by_Issuer4.txt | F183: has
A184: XX Program - 254(166 XX; 86 eSpace )\Monthly -117 (89 XX; 28 eSpace)\Customer_Profile.txt | B184: =IFERROR(LEFT(A184,FIND("~",SUBSTITUTE(A184,"\","~",LEN(A184)-LEN(SUBSTITUTE(A184,"\",""))))),"") | C184: =IFERROR(MID(A184,FIND("~",SUBSTITUTE(A184,"\","~",LEN(A184)-LEN(SUBSTITUTE(A184,"\",""))))+1,LEN(A184)),A184) | D184: 4268 | E184: E:\XX\Revenue by RM\adhoc\FD_Transaction.txt | F184: has
A185: XX Program - 254(166 XX; 86 eSpace )\Monthly -117 (89 XX; 28 eSpace)\eSpace -28\Report - CA Line Usage and Revenue Report - 2\ca_bal_summary.txt | B185: =IFERROR(LEFT(A185,FIND("~",SUBSTITUTE(A185,"\","~",LEN(A185)-LEN(SUBSTITUTE(A185,"\",""))))),"") | C185: =IFERROR(MID(A185,FIND("~",SUBSTITUTE(A185,"\","~",LEN(A185)-LEN(SUBSTITUTE(A185,"\",""))))+1,LEN(A185)),A185) | D185: 2 | E185: P:\Libname.txt
A186: XX Program - 254(166 XX; 86 eSpace )\Monthly -117 (89 XX; 28 eSpace)\eSpace -28\Report - CA Line Usage and Revenue Report - 2\import_export_bal.txt | B186: =IFERROR(LEFT(A186,FIND("~",SUBSTITUTE(A186,"\","~",LEN(A186)-LEN(SUBSTITUTE(A186,"\",""))))),"") | C186: =IFERROR(MID(A186,FIND("~",SUBSTITUTE(A186,"\","~",LEN(A186)-LEN(SUBSTITUTE(A186,"\",""))))+1,LEN(A186)),A186) | D186: 2 | E186: P:\Libname.txt
A187: XX Program - 254(166 XX; 86 eSpace )\Monthly -117 (89 XX; 28 eSpace)\eSpace -28\Report - Corporate Account with Tiered Interest Rate - 1\Corp_Prem_Rolling.txt | B187: =IFERROR(LEFT(A187,FIND("~",SUBSTITUTE(A187,"\","~",LEN(A187)-LEN(SUBSTITUTE(A187,"\",""))))),"") | C187: =IFERROR(MID(A187,FIND("~",SUBSTITUTE(A187,"\","~",LEN(A187)-LEN(SUBSTITUTE(A187,"\",""))))+1,LEN(A187)),A187) | D187: 46 | E187: E:\XX\Revenue by RM\Davin\Read_RM_Unit_Mapping.txt
A188: XX Program - 254(166 XX; 86 eSpace )\Monthly -117 (89 XX; 28 eSpace)\eSpace -28\Report - Loan and Deposit Average Balances - 8\$XX_Avgbal_Run.txt | B188: =IFERROR(LEFT(A188,FIND("~",SUBSTITUTE(A188,"\","~",LEN(A188)-LEN(SUBSTITUTE(A188,"\",""))))),"") | C188: =IFERROR(MID(A188,FIND("~",SUBSTITUTE(A188,"\","~",LEN(A188)-LEN(SUBSTITUTE(A188,"\",""))))+1,LEN(A188)),A188) | D188: 16 | E188: &PGM_PATH.00_Format_Creation.txt
A189: XX Program - 254(166 XX; 86 eSpace )\Monthly -117 (89 XX; 28 eSpace)\eSpace -28\Report - Loan and Deposit Average Balances - 8\$XX_Avgbal_Run.txt | B189: =IFERROR(LEFT(A189,FIND("~",SUBSTITUTE(A189,"\","~",LEN(A189)-LEN(SUBSTITUTE(A189,"\",""))))),"") | C189: =IFERROR(MID(A189,FIND("~",SUBSTITUTE(A189,"\","~",LEN(A189)-LEN(SUBSTITUTE(A189,"\",""))))+1,LEN(A189)),A189) | D189: 17 | E189: &PGM_PATH.01_Source.txt
A190: XX Program - 254(166 XX; 86 eSpace )\Monthly -117 (89 XX; 28 eSpace)\eSpace -28\Report - Loan and Deposit Average Balances - 8\$XX_Avgbal_Run.txt | B190: =IFERROR(LEFT(A190,FIND("~",SUBSTITUTE(A190,"\","~",LEN(A190)-LEN(SUBSTITUTE(A190,"\",""))))),"") | C190: =IFERROR(MID(A190,FIND("~",SUBSTITUTE(A190,"\","~",LEN(A190)-LEN(SUBSTITUTE(A190,"\",""))))+1,LEN(A190)),A190) | D190: 18 | E190: &PGM_PATH.02_Outdata.txt
A191: XX Program - 254(166 XX; 86 eSpace )\Monthly -117 (89 XX; 28 eSpace)\eSpace -28\Report - Loan and Deposit Average Balances - 8\00_Format_Creation.txt | B191: =IFERROR(LEFT(A191,FIND("~",SUBSTITUTE(A191,"\","~",LEN(A191)-LEN(SUBSTITUTE(A191,"\",""))))),"") | C191: =IFERROR(MID(A191,FIND("~",SUBSTITUTE(A191,"\","~",LEN(A191)-LEN(SUBSTITUTE(A191,"\",""))))+1,LEN(A191)),A191) | D191: 16 | E191: P:\Libname.txt
A192: XX Program - 254(166 XX; 86 eSpace )\Monthly -117 (89 XX; 28 eSpace)\eSpace -28\Report - Loan and Deposit Average Balances - 8\00_Format_Creation.txt | B192: =IFERROR(LEFT(A192,FIND("~",SUBSTITUTE(A192,"\","~",LEN(A192)-LEN(SUBSTITUTE(A192,"\",""))))),"") | C192: =IFERROR(MID(A192,FIND("~",SUBSTITUTE(A192,"\","~",LEN(A192)-LEN(SUBSTITUTE(A192,"\",""))))+1,LEN(A192)),A192) | D192: 134 | E192: E:\XX\Revenue by RM\Davin\Read_RM_Unit_Mapping.txt
A193: XX Program - 254(166 XX; 86 eSpace )\Monthly -117 (89 XX; 28 eSpace)\eSpace -28\Report - Loan and Deposit Average Balances - 8\Bills_Asset_Trend.txt | B193: =IFERROR(LEFT(A193,FIND("~",SUBSTITUTE(A193,"\","~",LEN(A193)-LEN(SUBSTITUTE(A193,"\",""))))),"") | C193: =IFERROR(MID(A193,FIND("~",SUBSTITUTE(A193,"\","~",LEN(A193)-LEN(SUBSTITUTE(A193,"\",""))))+1,LEN(A193)),A193) | D193: 3 | E193: P:\Libname.txt
A194: XX Program - 254(166 XX; 86 eSpace )\Monthly -117 (89 XX; 28 eSpace)\eSpace -28\Report - Loan and Deposit Average Balances - 8\bills_full_run.txt | B194: =IFERROR(LEFT(A194,FIND("~",SUBSTITUTE(A194,"\","~",LEN(A194)-LEN(SUBSTITUTE(A194,"\",""))))),"") | C194: =IFERROR(MID(A194,FIND("~",SUBSTITUTE(A194,"\","~",LEN(A194)-LEN(SUBSTITUTE(A194,"\",""))))+1,LEN(A194)),A194) | D194: 3 | E194: P:\Libname.txt
A195: XX Program - 254(166 XX; 86 eSpace )\Monthly -117 (89 XX; 28 eSpace)\eSpace -28\Report - Loan and Deposit Average Balances - 8\bills_full_run.txt | B195: =IFERROR(LEFT(A195,FIND("~",SUBSTITUTE(A195,"\","~",LEN(A195)-LEN(SUBSTITUTE(A195,"\",""))))),"") | C195: =IFERROR(MID(A195,FIND("~",SUBSTITUTE(A195,"\","~",LEN(A195)-LEN(SUBSTITUTE(A195,"\",""))))+1,LEN(A195)),A195) | D195: 119 | E195: &PGM_PATH.Bills_Asset_Trend.txt
A196: XX Program - 254(166 XX; 86 eSpace )\Monthly -117 (89 XX; 28 eSpace)\eSpace -28\Report - Loan and Deposit Average Balances - 8\bills_full_run.txt | B196: =IFERROR(LEFT(A196,FIND("~",SUBSTITUTE(A196,"\","~",LEN(A196)-LEN(SUBSTITUTE(A196,"\",""))))),"") | C196: =IFERROR(MID(A196,FIND("~",SUBSTITUTE(A196,"\","~",LEN(A196)-LEN(SUBSTITUTE(A196,"\",""))))+1,LEN(A196)),A196) | D196: 120 | E196: &PGM_PATH.Bills_Commission_turnover.txt
... A313: XX Program - 254(166 XX; 86 eSpace )\On request -14 (13 XX; 1 eSpace)\WBG Customer_Emily.txt | B313: =IFERROR(LEFT(A313,FIND("~",SUBSTITUTE(A313,"\","~",LEN(A313)-LEN(SUBSTITUTE(A313,"\",""))))),"") | C313: =IFERROR(MID(A313,FIND("~",SUBSTITUTE(A313,"\","~",LEN(A313)-LEN(SUBSTITUTE(A313,"\",""))))+1,LEN(A313)),A313) | D313: 5 | E313: p:\libname.txt

Sheet Frequency
A1: p:\libname.txt | B1: =COUNTIF(Include_Relationship!E:E,A1)
A2: E:\XX\Revenue by RM\Macro\Set_Macro.txt | B2: =COUNTIF(Include_Relationship!E:E,A2)
A3: &Macro_Path.Set_Macro.txt | B3: =COUNTIF(Include_Relationship!E:E,A3)
A4: E:\XX\Celia\libname.txt | B4: =COUNTIF(Include_Relationship!E:E,A4)
A5: E:\XX\Revenue by RM\Report\Analysis\Daily_Issue_Bank.txt | B5: =COUNTIF(Include_Relationship!E:E,A5)
A6: E:\XX\Revenue by RM\Report\Analysis\Daily_CASA_Trend4.txt | B6: =COUNTIF(Include_Relationship!E:E,A6)
A7: E:\XX\Revenue by RM\Report\Analysis\Daily_New_Loan_Pricing3.txt | B7: =COUNTIF(Include_Relationship!E:E,A7)
A8: E:\XX\Daily_Deposit_Movement\Read_MBR_Deposit2.txt | B8: =COUNTIF(Include_Relationship!E:E,A8)
A9: E:\XX\Daily_Deposit_Movement\Read_SG_Deposit.txt | B9: =COUNTIF(Include_Relationship!E:E,A9)
A10: &FEE_REPORT_PATH.\Program\Dev\Generate_Report.txt | B10: =COUNTIF(Include_Relationship!E:E,A10)
A11: &FEE_REPORT_PATH.\Program\Dev\Generate_Fee_Income_Report.txt | B11: =COUNTIF(Include_Relationship!E:E,A11)
A12: &FEE_REPORT_PATH.\Program\Dev\Generate_Fee_Amort_File.txt | B12: =COUNTIF(Include_Relationship!E:E,A12)
... A105: E:\XX\Revenue by RM\Report\Analysis\Export_IW_Amort.txt | B105: =COUNTIF(Include_Relationship!E:E,A105)
